{
  "masks": {
    "XXXXXDDDD": 3,
    "XXXXXSDDDD": 3,
    "XXXXXDD": 1,
    "XXXXXDDS": 1,
    "XXXXXSDD": 2,
    "DDDDXXXXX": 2,
    "DDXXXXXS": 1,
    "XXXXXDDDDS": 1,
    "XXXXXDDDDXXXX": 1
  },
  "numbers": {
    "4": 15,
    "0": 15,
    "2": 10
  },
  "words": {
    "mer": 5,
    "ere": 15,
    "rei": 14,
    "ei2": 4,
    "i20": 4,
    "200": 10,
    "004": 10,
    "mere": 5,
    "erei": 14,
    "rei2": 4,
    "ei20": 4,
    "i200": 4,
    "2004": 10,
    "merei": 4,
    "erei2": 4,
    "rei20": 4,
    "ei200": 4,
    "i2004": 4,
    "merei2": 1,
    "erei20": 4,
    "rei200": 4,
    "ei2004": 4,
    "merei20": 1,
    "erei200": 4,
    "rei2004": 4,
    "Mer": 10,
    "Mere": 10,
    "Merei": 10,
    "Merei2": 3,
    "Merei20": 3,
    "ei_": 2,
    "i_2": 1,
    "_20": 1,
    "rei_": 2,
    "ei_2": 1,
    "i_20": 1,
    "_200": 1,
    "erei_": 2,
    "rei_2": 1,
    "ei_20": 1,
    "i_200": 1,
    "_2004": 1,
    "Merei_": 1,
    "erei_2": 1,
    "rei_20": 1,
    "ei_200": 1,
    "i_2004": 1,
    "Merei_2": 1,
    "erei_20": 1,
    "rei_200": 1,
    "ei_2004": 1,
    "ei#": 1,
    "i#2": 1,
    "#20": 1,
    "rei#": 1,
    "ei#2": 1,
    "i#20": 1,
    "#200": 1,
    "erei#": 1,
    "rei#2": 1,
    "ei#20": 1,
    "i#200": 1,
    "#2004": 1,
    "Merei#": 1,
    "erei#2": 1,
    "rei#20": 1,
    "ei#200": 1,
    "i#2004": 1,
    "Merei#2": 1,
    "erei#20": 1,
    "rei#200": 1,
    "ei#2004": 1,
    "ei0": 2,
    "i04": 2,
    "rei0": 2,
    "ei04": 2,
    "erei0": 2,
    "rei04": 2,
    "Merei0": 1,
    "erei04": 2,
    "Merei04": 1,
    "rey": 1,
    "ey2": 1,
    "y20": 1,
    "erey": 1,
    "rey2": 1,
    "ey20": 1,
    "y200": 1,
    "merey": 1,
    "erey2": 1,
    "rey20": 1,
    "ey200": 1,
    "y2004": 1,
    "merey2": 1,
    "erey20": 1,
    "rey200": 1,
    "ey2004": 1,
    "merey20": 1,
    "erey200": 1,
    "rey2004": 1,
    "04!": 2,
    "i04!": 1,
    "ei04!": 1,
    "merei0": 1,
    "rei04!": 1,
    "merei04": 1,
    "erei04!": 1,
    "ei*": 1,
    "i*0": 1,
    "*04": 1,
    "rei*": 1,
    "ei*0": 1,
    "i*04": 1,
    "erei*": 1,
    "rei*0": 1,
    "ei*04": 1,
    "Merei*": 1,
    "erei*0": 1,
    "rei*04": 1,
    "Merei*0": 1,
    "erei*04": 1,
    "i_0": 1,
    "_04": 1,
    "ei_0": 1,
    "i_04": 1,
    "rei_0": 1,
    "ei_04": 1,
    "merei_": 1,
    "erei_0": 1,
    "rei_04": 1,
    "merei_0": 1,
    "erei_04": 1,
    "ei-": 1,
    "i-2": 1,
    "-20": 1,
    "rei-": 1,
    "ei-2": 1,
    "i-20": 1,
    "-200": 1,
    "erei-": 1,
    "rei-2": 1,
    "ei-20": 1,
    "i-200": 1,
    "-2004": 1,
    "Merei-": 1,
    "erei-2": 1,
    "rei-20": 1,
    "ei-200": 1,
    "i-2004": 1,
    "Merei-2": 1,
    "erei-20": 1,
    "rei-200": 1,
    "ei-2004": 1,
    "04m": 1,
    "4me": 1,
    "004m": 1,
    "04me": 1,
    "4mer": 1,
    "2004m": 1,
    "004me": 1,
    "04mer": 1,
    "4mere": 1,
    "2004me": 1,
    "004mer": 1,
    "04mere": 1,
    "4merei": 1,
    "2004mer": 1,
    "004mere": 1,
    "04merei": 1,
    "04M": 2,
    "4Me": 2,
    "004M": 1,
    "04Me": 2,
    "4Mer": 2,
    "2004M": 1,
    "004Me": 1,
    "04Mer": 2,
    "4Mere": 2,
    "2004Me": 1,
    "004Mer": 1,
    "04Mere": 2,
    "4Merei": 2,
    "2004Mer": 1,
    "004Mere": 1,
    "04Merei": 2,
    "ei!": 1,
    "rei!": 1,
    "erei!": 1,
    "Merei!": 1,
    "4Merei!": 1,
    "004!": 1,
    "2004!": 1,
    "i2004!": 1,
    "ei2004!": 1,
    "04p": 1,
    "4pa": 1,
    "pas": 1,
    "ass": 1,
    "004p": 1,
    "04pa": 1,
    "4pas": 1,
    "pass": 1,
    "2004p": 1,
    "004pa": 1,
    "04pas": 1,
    "4pass": 1,
    "i2004p": 1,
    "2004pa": 1,
    "004pas": 1,
    "04pass": 1,
    "ei2004p": 1,
    "i2004pa": 1,
    "2004pas": 1,
    "004pass": 1
  },
  "zigzag": 10
}